mlx/__main__.py
mlx/_os_warning.py
mlx/_reprlib_fix.py
mlx/distributed_run.py
mlx/extension.py
mlx/mlx.pyi
mlx/py.typed
mlx/utils.py
mlx/include/metal_cpp/LICENSE.txt
mlx/include/metal_cpp/README.md
mlx/include/metal_cpp/Foundation/Foundation.hpp
mlx/include/metal_cpp/Foundation/NSArray.hpp
mlx/include/metal_cpp/Foundation/NSAutoreleasePool.hpp
mlx/include/metal_cpp/Foundation/NSBundle.hpp
mlx/include/metal_cpp/Foundation/NSData.hpp
mlx/include/metal_cpp/Foundation/NSDate.hpp
mlx/include/metal_cpp/Foundation/NSDefines.hpp
mlx/include/metal_cpp/Foundation/NSDictionary.hpp
mlx/include/metal_cpp/Foundation/NSEnumerator.hpp
mlx/include/metal_cpp/Foundation/NSError.hpp
mlx/include/metal_cpp/Foundation/NSLock.hpp
mlx/include/metal_cpp/Foundation/NSNotification.hpp
mlx/include/metal_cpp/Foundation/NSNumber.hpp
mlx/include/metal_cpp/Foundation/NSObjCRuntime.hpp
mlx/include/metal_cpp/Foundation/NSObject.hpp
mlx/include/metal_cpp/Foundation/NSPrivate.hpp
mlx/include/metal_cpp/Foundation/NSProcessInfo.hpp
mlx/include/metal_cpp/Foundation/NSRange.hpp
mlx/include/metal_cpp/Foundation/NSSet.hpp
mlx/include/metal_cpp/Foundation/NSSharedPtr.hpp
mlx/include/metal_cpp/Foundation/NSString.hpp
mlx/include/metal_cpp/Foundation/NSTypes.hpp
mlx/include/metal_cpp/Foundation/NSURL.hpp
mlx/include/metal_cpp/Metal/MTLAccelerationStructure.hpp
mlx/include/metal_cpp/Metal/MTLAccelerationStructureCommandEncoder.hpp
mlx/include/metal_cpp/Metal/MTLAccelerationStructureTypes.hpp
mlx/include/metal_cpp/Metal/MTLAllocation.hpp
mlx/include/metal_cpp/Metal/MTLArgument.hpp
mlx/include/metal_cpp/Metal/MTLArgumentEncoder.hpp
mlx/include/metal_cpp/Metal/MTLBinaryArchive.hpp
mlx/include/metal_cpp/Metal/MTLBlitCommandEncoder.hpp
mlx/include/metal_cpp/Metal/MTLBlitPass.hpp
mlx/include/metal_cpp/Metal/MTLBuffer.hpp
mlx/include/metal_cpp/Metal/MTLCaptureManager.hpp
mlx/include/metal_cpp/Metal/MTLCaptureScope.hpp
mlx/include/metal_cpp/Metal/MTLCommandBuffer.hpp
mlx/include/metal_cpp/Metal/MTLCommandEncoder.hpp
mlx_metal_awni_test-0.26.5.dist-info/licenses/LICENSE
mlx_metal_awni_test-0.26.5.dist-info/METADATA
mlx_metal_awni_test-0.26.5.dist-info/WHEEL
mlx_metal_awni_test-0.26.5.dist-info/top_level.txt
mlx_metal_awni_test-0.26.5.dist-info/RECORD
